PyQt6/Qt6/qsci/api/python/PyQt6-Graphs.api
PyQt6/QtGraphs.abi3.so
PyQt6/QtGraphs.pyi
PyQt6/QtGraphsWidgets.abi3.so
PyQt6/QtGraphsWidgets.pyi
PyQt6/bindings/QtGraphs/QtGraphs.toml
PyQt6/bindings/QtGraphs/QtGraphsmod.sip
PyQt6/bindings/QtGraphs/q3dscene.sip
PyQt6/bindings/QtGraphs/qabstract3daxis.sip
PyQt6/bindings/QtGraphs/qabstract3dseries.sip
PyQt6/bindings/QtGraphs/qabstractaxis.sip
PyQt6/bindings/QtGraphs/qabstractdataproxy.sip
PyQt6/bindings/QtGraphs/qabstractseries.sip
PyQt6/bindings/QtGraphs/qareaseries.sip
PyQt6/bindings/QtGraphs/qbar3dseries.sip
PyQt6/bindings/QtGraphs/qbarcategoryaxis.sip
PyQt6/bindings/QtGraphs/qbardataitem.sip
PyQt6/bindings/QtGraphs/qbardataproxy.sip
PyQt6/bindings/QtGraphs/qbarmodelmapper.sip
PyQt6/bindings/QtGraphs/qbarseries.sip
PyQt6/bindings/QtGraphs/qbarset.sip
PyQt6/bindings/QtGraphs/qcategory3daxis.sip
PyQt6/bindings/QtGraphs/qcustom3ditem.sip
PyQt6/bindings/QtGraphs/qcustom3dlabel.sip
PyQt6/bindings/QtGraphs/qcustom3dvolume.sip
PyQt6/bindings/QtGraphs/qdatetimeaxis.sip
PyQt6/bindings/QtGraphs/qgraphs3dnamespace.sip
PyQt6/bindings/QtGraphs/qgraphstheme.sip
PyQt6/bindings/QtGraphs/qheightmapsurfacedataproxy.sip
PyQt6/bindings/QtGraphs/qitemmodelbardataproxy.sip
PyQt6/bindings/QtGraphs/qitemmodelscatterdataproxy.sip
PyQt6/bindings/QtGraphs/qitemmodelsurfacedataproxy.sip
PyQt6/bindings/QtGraphs/qlineseries.sip
PyQt6/bindings/QtGraphs/qlist.sip
PyQt6/bindings/QtGraphs/qlogvalue3daxisformatter.sip
PyQt6/bindings/QtGraphs/qpiemodelmapper.sip
PyQt6/bindings/QtGraphs/qpieseries.sip
PyQt6/bindings/QtGraphs/qpieslice.sip
PyQt6/bindings/QtGraphs/qscatter3dseries.sip
PyQt6/bindings/QtGraphs/qscatterdataitem.sip
PyQt6/bindings/QtGraphs/qscatterdataproxy.sip
PyQt6/bindings/QtGraphs/qscatterseries.sip
PyQt6/bindings/QtGraphs/qspline3dseries.sip
PyQt6/bindings/QtGraphs/qsplineseries.sip
PyQt6/bindings/QtGraphs/qsurface3dseries.sip
PyQt6/bindings/QtGraphs/qsurfacedataitem.sip
PyQt6/bindings/QtGraphs/qsurfacedataproxy.sip
pyqt6_graphs-6.10.0.dist-info/licenses/LICENSE
pyqt6_graphs-6.10.0.dist-info/WHEEL
pyqt6_graphs-6.10.0.dist-info/METADATA
pyqt6_graphs-6.10.0.dist-info/RECORD
