Metadata-Version: 2.4
Name: PyQt6-Graphs
Version: 6.10.0
Requires-Python: >=3.9
Summary: Python bindings for the Qt Graphs library
Project-Url: homepage, https://www.riverbankcomputing.com/software/pyqtgraphs/
Requires-Dist: PyQt6-sip (>=13.8, <14)
Requires-Dist: PyQt6-Graphs-Qt6 (>=6.10.0, <6.11.0)
Requires-Dist: PyQt6 (>=6.8.0)
License-Expression: GPL-3.0-only
License-File: LICENSE
Author-Email: Riverbank Computing Limited <info@riverbankcomputing.com>
